{
  "type": "minecraft:crafting_shaped",
  "category": "redstone",
  "pattern": [
    "aba",
    "cdc",
    "aea"
  ],
  "key": {
    "a": {
      "item": "minecraft:copper_ingot"
    },
    "b": {
      "item": "minecraft:redstone"
    },
    "c": {
      "item": "minecraft:copper_block"
    },
    "d": {
      "item": "superiorstructures:lightning_charge"
    },
    "e": {
      "item": "superiorstructures:broken_machinery"
    }
  },
  "result": {
    "id": "superiorstructures:lightning_coil",
    "count": 4
  }
}